{
  "_id": "TECXR5BEZFzL5Tmo",
  "name": "Stilt Steps",
  "type": "power",
  "img": "systems/marvel-multiverse/icons/placticity.svg",
  "system": {
    "description": "The character can stretch their legs like extendable stilts.",
    "powerSet": "Plasticity",
    "prerequisites": "Extended Reach 1, Rank 2",
    "action": "Movement",
    "trigger": "",
    "duration": "Concentration",
    "range": "",
    "cost": "",
    "effect": "The character's Run Speed doubles, as does their Climb Speed."
  },
  "flags": {},
  "effects": [
    {
      "name": "Double Run Speed",
      "img": "icons/svg/aura.svg",
      "duration": {
        "startTime": null,
        "seconds": null,
        "combat": null,
        "rounds": null,
        "turns": null,
        "startRound": null,
        "startTurn": null
      },
      "disabled": false,
      "origin": "Item.TECXR5BEZFzL5Tmo",
      "_id": "2de0ec2e33f44ed7",
      "changes": [
        {
          "key": "system.movement.run.calc",
          "mode": 1,
          "value": 2
        }
      ],
      "description": "",
      "transfer": true,
      "statuses": [],
      "flags": {},
      "tint": null,
      "_key": "!items.effects!TECXR5BEZFzL5Tmo.2de0ec2e33f44ed7"
    },
    {
      "name": "Double Climb Speed",
      "img": "icons/svg/aura.svg",
      "duration": {
        "startTime": null,
        "seconds": null,
        "combat": null,
        "rounds": null,
        "turns": null,
        "startRound": null,
        "startTurn": null
      },
      "disabled": false,
      "origin": "Item.TECXR5BEZFzL5Tmo",
      "_id": "a63fb94513a84abc",
      "changes": [
        {
          "key": "system.movement.climb.calc",
          "mode": 1,
          "value": 2
        }
      ],
      "description": "",
      "transfer": true,
      "statuses": [],
      "flags": {},
      "tint": null,
      "_key": "!items.effects!TECXR5BEZFzL5Tmo.a63fb94513a84abc"
    }
  ],
  "folder": "b660cb39178688a5",
  "_key": "!items!TECXR5BEZFzL5Tmo"
}
