{
  "_id": "VLbgw5shFgAQcYDI",
  "name": "Postcognition 3",
  "type": "power",
  "img": "systems/marvel-multiverse/icons/super-powers.svg",
  "system": {
    "description": "The character knows what happened in the past year.",
    "powerSet": "Sixth Sense",
    "prerequisites": "Postcognition 2. Rank 4",
    "action": "Standard",
    "trigger": "",
    "duration": "Instant",
    "range": "",
    "cost": "20 Focus",
    "effect": "The character can sense what happened to a particular person, place, or item within their reach-including themselves in any 24 hour period in the past year. Otherwise it works the same as Postcognition 1.",
    "numbered": 2
  },
  "flags": {},
  "effects": [],
  "folder": "34a53ed3fba44fe3",
  "_key": "!items!VLbgw5shFgAQcYDI"
}
