{
  "_id": "46f5e81a-21e3-406e-8608-ef478f741511",
  "name": "Operations Center",
  "type": "power",
  "system": {
    "description": "The character directs their allies in combat.",
    "powerSet": "Tactics",
    "prerequisites": "Combat Support, Focus Fire, Rank 4",
    "action": "Standard",
    "trigger": "",
    "duration": "Concentration",
    "range": "",
    "cost": "15 focus",
    "effect": "The character inspires one or more allies of their choice in earshot, up to the character's Vigilance defense. Affected allies gain an edge on all action checks until the start of the character's next turn. The character breaks concentration on this power if they use a movement action."
  },
  "flags": {},
  "effects": [],
  "_key": "!items!46f5e81a-21e3-406e-8608-ef478f741511"
}
