{
  "_id": "852e859c-6895-4bd9-8884-6d2082d72701",
  "name": "Early Bloomer",
  "type": "tag",
  "system": {
    "description": "The character is a rare kind of throwback mutant who gained their powers at birth. In most cases, this means their parents hid their powers as long as they could-or that the authorities took charge of them early on, supposedly for everyone's protection.",
    "restriction": "",
    "rarity": ""
  },
  "flags": {},
  "effects": [],
  "_key": "!items!852e859c-6895-4bd9-8884-6d2082d72701"
}
